tabbench/VERSION.txt
tabbench/__init__.py
tabbench/datasets/__init__.py
tabbench/datasets/openml/1038.py
tabbench/datasets/openml/1049.py
tabbench/datasets/openml/1050.py
tabbench/datasets/openml/1063.py
tabbench/datasets/openml/1067.py
tabbench/datasets/openml/1068.py
tabbench/datasets/openml/11.py
tabbench/datasets/openml/12.py
tabbench/datasets/openml/14.py
tabbench/datasets/openml/1462.py
tabbench/datasets/openml/1464.py
tabbench/datasets/openml/1471.py
tabbench/datasets/openml/1475.py
tabbench/datasets/openml/1480.py
tabbench/datasets/openml/1487.py
tabbench/datasets/openml/1489.py
tabbench/datasets/openml/1494.py
tabbench/datasets/openml/15.py
tabbench/datasets/openml/1510.py
tabbench/datasets/openml/16.py
tabbench/datasets/openml/179.py
tabbench/datasets/openml/18.py
tabbench/datasets/openml/181.py
tabbench/datasets/openml/188.py
tabbench/datasets/openml/20.py
tabbench/datasets/openml/22.py
tabbench/datasets/openml/23.py
tabbench/datasets/openml/23381.py
tabbench/datasets/openml/29.py
tabbench/datasets/openml/3.py
tabbench/datasets/openml/31.py
tabbench/datasets/openml/333.py
tabbench/datasets/openml/334.py
tabbench/datasets/openml/335.py
tabbench/datasets/openml/37.py
tabbench/datasets/openml/40498.py
tabbench/datasets/openml/40670.py
tabbench/datasets/openml/40701.py
tabbench/datasets/openml/40900.py
tabbench/datasets/openml/40966.py
tabbench/datasets/openml/40975.py
tabbench/datasets/openml/40981.py
tabbench/datasets/openml/40982.py
tabbench/datasets/openml/40983.py
tabbench/datasets/openml/40984.py
tabbench/datasets/openml/40994.py
tabbench/datasets/openml/41021.py
tabbench/datasets/openml/41143.py
tabbench/datasets/openml/41144.py
tabbench/datasets/openml/41145.py
tabbench/datasets/openml/41146.py
tabbench/datasets/openml/41156.py
tabbench/datasets/openml/44.py
tabbench/datasets/openml/44956.py
tabbench/datasets/openml/44957.py
tabbench/datasets/openml/44958.py
tabbench/datasets/openml/44959.py
tabbench/datasets/openml/44960.py
tabbench-0.0.1.dist-info/licenses/LICENSE
tabbench-0.0.1.dist-info/METADATA
tabbench-0.0.1.dist-info/WHEEL
tabbench-0.0.1.dist-info/top_level.txt
tabbench-0.0.1.dist-info/RECORD
