Metadata-Version: 2.4
Name: tabbench
Version: 0.0.1
Summary: Datasets and scripts for tabular benchmark.
Author-email: Neuralk AI Research Team <alex@neuralk-ai.com>, Alexandre Pasquiou <alex@neuralk-ai.com>, Alexandre Abraham <alexandre.abraham@neuralk-ai.com>, Frosso Papanastasiou <frosso.papanastasiou@neuralk-ai.com>
Maintainer-email: Neuralk AI Research Team <alex@neuralk-ai.com>
Project-URL: Homepage, https://neuralk-ai.com
Project-URL: Documentation, https://readthedocs.org
Project-URL: Repository, https://github.com/Neuralk-AI/tabbench
Classifier: Development Status :: 3 - Alpha
Classifier: Intended Audience :: Science/Research
Classifier: Programming Language :: Python :: 3.10
Classifier: Programming Language :: Python :: 3.11
Classifier: Programming Language :: Python :: 3.12
Classifier: License :: OSI Approved :: Apache Software License
Classifier: Operating System :: OS Independent
Requires-Python: >=3.9
License-File: LICENSE
Requires-Dist: openml>=0.15.1
Requires-Dist: neuralk_foundry_ce>=0.0.2
Dynamic: license-file
